MPSTools/VERSION
MPSTools/__init__.py
MPSTools/__pycache__/__init__.cpython-310.pyc
MPSTools/fiber_catalogue/__init__.py
MPSTools/fiber_catalogue/loader.py
MPSTools/fiber_catalogue/__pycache__/__init__.cpython-310.pyc
MPSTools/fiber_catalogue/__pycache__/loader.cpython-310.pyc
MPSTools/fiber_catalogue/fiber_files/1550BHP.yaml
MPSTools/fiber_catalogue/fiber_files/DCF13.yaml
MPSTools/fiber_catalogue/fiber_files/DCF1300S_20.yaml
MPSTools/fiber_catalogue/fiber_files/DCF1300S_26.yaml
MPSTools/fiber_catalogue/fiber_files/DCF1300S_33.yaml
MPSTools/fiber_catalogue/fiber_files/DCF1300S_42.yaml
MPSTools/fiber_catalogue/fiber_files/F2028M12.yaml
MPSTools/fiber_catalogue/fiber_files/F2028M21.yaml
MPSTools/fiber_catalogue/fiber_files/F2028M24.yaml
MPSTools/fiber_catalogue/fiber_files/F2058G1.yaml
MPSTools/fiber_catalogue/fiber_files/F2058L1.yaml
MPSTools/fiber_catalogue/fiber_files/HI1060.yaml
MPSTools/fiber_catalogue/fiber_files/HP630.yaml
MPSTools/fiber_catalogue/fiber_files/SM1950.yaml
MPSTools/fiber_catalogue/fiber_files/SMF28.yaml
MPSTools/fiber_catalogue/fiber_files/fluorine_doped_1%_capillary.yaml
MPSTools/fiber_catalogue/fiber_files/fluorine_doped_2%_capillary.yaml
MPSTools/fiber_catalogue/fiber_files/test_fiber.yaml
MPSTools/fiber_catalogue/fiber_files/test_multimode_fiber.yaml
MPSTools/material_catalogue/__init__.py
MPSTools/material_catalogue/loader.py
MPSTools/material_catalogue/__pycache__/__init__.cpython-310.pyc
MPSTools/material_catalogue/__pycache__/loader.cpython-310.pyc
MPSTools/material_catalogue/material_files/measurements/__init__.py
MPSTools/material_catalogue/material_files/measurements/aluminium.yaml
MPSTools/material_catalogue/material_files/measurements/ethanol.yaml
MPSTools/material_catalogue/material_files/measurements/gold.yaml
MPSTools/material_catalogue/material_files/measurements/iron.yaml
MPSTools/material_catalogue/material_files/measurements/polystyrene.yaml
MPSTools/material_catalogue/material_files/measurements/silver.yaml
MPSTools-1.2.1.dist-info/LICENSE
MPSTools-1.2.1.dist-info/METADATA
MPSTools-1.2.1.dist-info/WHEEL
MPSTools-1.2.1.dist-info/top_level.txt
MPSTools-1.2.1.dist-info/RECORD
